src/__init__.py
src/cli.py
src/config.py
src/hooks.py
src/init.py
src/install.py
src/logger.py
src/ls.py
src/run.py
src/sanitize.py
src/version.py
test/__init__.py
test/test_cli.py
barb-0.2.5.dist-info/METADATA
barb-0.2.5.dist-info/WHEEL
barb-0.2.5.dist-info/entry_points.txt
barb-0.2.5.dist-info/top_level.txt
barb-0.2.5.dist-info/RECORD
