Metadata-Version: 2.1
Name: barb
Version: 0.2.5
Summary: Hassle free git hooks for python projects.
Home-page: https://github.com/jettdc/barb
Author: Jett Crowson
Author-email: jettcrowson@gmail.com
License: MIT
Keywords: hooks git githooks automation git-hooks git-hook
Platform: UNKNOWN
Requires-Python: >=3.5
Requires-Dist: toml
Requires-Dist: python-dotenv
Requires-Dist: jetts-tools
